hwscan/__about__.py
hwscan/__init__.py
hwscan/cli.py
hwscan/scanner.py
hwscan/hardware/__init__.py
hwscan/hardware/arduino_leonardo.py
hwscan/hardware/esp32-c5-wroom.py
hwscan/hardware/host.py
hwscan/hardware/jlink.py
hwscan/hardware/stlinkv3.py
hwscan/hardware/trilightsense.py
hwscan/hardware/uart_to_dmx.py
hwscan/hardware/util.py
lumenradio_hwscan-0.4.0.dist-info/METADATA
lumenradio_hwscan-0.4.0.dist-info/WHEEL
lumenradio_hwscan-0.4.0.dist-info/entry_points.txt
lumenradio_hwscan-0.4.0.dist-info/top_level.txt
lumenradio_hwscan-0.4.0.dist-info/RECORD
