Metadata-Version: 2.4
Name: lumenradio-hwscan
Version: 0.4.0
Summary: Hardware detector CLI for USB serial/debug devices (TriLightSense, STLINK-V3, ESP32, host info).
Author-email: Jonas Estberger <jonas.estberger@lumenradio.com>
License: MIT
Keywords: usb,serial,udev,hardware,detector,TriLightSense,stlink,espressif,jlink
Classifier: Programming Language :: Python :: 3
Classifier: License :: OSI Approved :: MIT License
Classifier: Operating System :: POSIX :: Linux
Classifier: Environment :: Console
Classifier: Topic :: System :: Hardware
Classifier: Topic :: System :: Operating System Kernels :: Linux
Requires-Python: >=3.8
Provides-Extra: dev
Requires-Dist: build>=1.2.1; extra == "dev"
Requires-Dist: twine>=5.1.1; extra == "dev"
Requires-Dist: wheel; extra == "dev"
Requires-Dist: black>=25.9.0; extra == "dev"
